[
  {"id": 1,"name": "Wood","imgURL": "24px-Wood"},
  {"id": 2,"name": "Stone","imgURL": "24px-Stone"},
  {"id": 3,"name": "Coal","imgURL": "24px-Coal"},
  {"id": 4,"name": "Copper Bar","imgURL": "24px-Copper_Bar"},
  {"id": 5,"name": "Iron Bar","imgURL": "24px-Iron_Bar"},
  {"id": 6,"name": "Gold Bar","imgURL": "24px-Gold_Bar"},
  {"id": 7,"name": "Refined Quartz","imgURL": "24px-Refined_Quartz"},
  {"id": 8,"name": "Earth Crystal","imgURL": "24px-Earth_Crystal"},
  {"id": 9,"name": "Maple Syrup","imgURL": "24px-Maple_Syrup"}
]